luck.py
luck-0.0.3.dist-info/WHEEL
luck-0.0.3.dist-info/METADATA
luck-0.0.3.dist-info/RECORD
