Metadata-Version: 1.2
Name: luck
Version: 0.0.3
Summary: this is the second version
Home-page: https://github.com/Carreau/luck
License: UNKNOWN
Author: Matthias Bussonnier
Author-email: bussonniermatthias@gmail.com
Classifier: License :: OSI Approved :: MIT License
